json_agg/__init__.py
json_agg/aggregates.py
json_agg/py.typed
django_json_agg-0.0.1.dist-info/LICENSE
django_json_agg-0.0.1.dist-info/METADATA
django_json_agg-0.0.1.dist-info/WHEEL
django_json_agg-0.0.1.dist-info/RECORD
