Metadata-Version: 2.1
Name: django-json-agg
Version: 0.0.1
Summary: Django JSON Agg
Home-page: https://github.com/quipucords/django-json-agg
License: GPL-3.0
Author: Discovery Team
Author-email: discovery@redhat.com
Requires-Python: >=3.8,<4.0
Classifier: Development Status :: 4 - Beta
Classifier: License :: OSI Approved :: GNU General Public License v3 (GPLv3)
Classifier: Programming Language :: Python :: 3
Classifier: Programming Language :: Python :: 3.8
Classifier: Programming Language :: Python :: 3.9
Classifier: Programming Language :: Python :: 3.10
Classifier: Programming Language :: Python :: 3.11
Classifier: Programming Language :: Python :: 3.12
Requires-Dist: django (>=4.2)
Project-URL: Changelog, https://github.com/quipucords/django-json-agg/releases
Project-URL: Documentation, https://django-json-agg.readthedocs.io
Project-URL: Repository, https://github.com/quipucords/django-json-agg
